industry/__init__.py
industry/admin.py
industry/app_settings.py
industry/apps.py
industry/auth_hooks.py
industry/forms.py
industry/helper.py
industry/models.py
industry/tasks.py
industry/tests.py
industry/urls.py
industry/views.py
industry/migrations/0001_initial.py
industry/migrations/0002_delete_usertoken.py
industry/migrations/0003_auto_20220601_1747.py
industry/migrations/0004_usercharacters.py
industry/migrations/__init__.py
industry/static/industry/images/Icon_Copying.png
industry/static/industry/images/Icon_Invention.png
industry/static/industry/images/Icon_Manufacturing.png
industry/static/industry/images/Icon_Reaction.png
industry/static/industry/images/Icon_ResearchMaterial.png
industry/static/industry/images/Icon_ReverseEngineering.png
industry/static/industry/images/copying.png
industry/static/industry/images/invention.png
industry/static/industry/images/manufacturing.png
industry/static/industry/images/reaction.png
industry/static/industry/images/researchMaterial.png
industry/static/industry/images/researchTime.png
industry/templates/industry/base.html
industry/templates/industry/corp_jobs_list_snippet.html
industry/templates/industry/index.html
industry/templates/industry/jobs_list_snippet.html
industry/templates/industry/registered_characters.html
industry/templates/industry/usertoken_confirm_delete.html
industry/templatetags/__init__.py
industry/templatetags/character_portrait.py
aa_industry-0.2.1.dist-info/METADATA
aa_industry-0.2.1.dist-info/WHEEL
aa_industry-0.2.1.dist-info/licenses/LICENSE
aa_industry-0.2.1.dist-info/RECORD
