Metadata-Version: 2.1
Name: aa-industry
Version: 0.2.1
Summary: Industry plugin app for Alliance Auth.
Project-URL: Homepage, https://github.com/aechiara/aa-industry
Project-URL: Documentation, https://github.com/aechiara/aa-industry
Project-URL: Source, https://github.com/aechiara/aa-industry
Project-URL: Changelog, https://github.com/aechiara/aa-industry
Project-URL: Tracker, https://github.com/aechiara/aa-industry/issues
Author-email: AlexBR Plasmodio <aechiara@gmail.com>
License-File: LICENSE
Keywords: allianceauth,eveonline,industry
Classifier: Environment :: Web Environment
Classifier: Framework :: Django
Classifier: Framework :: Django :: 4.0
Classifier: Intended Audience :: Developers
Classifier: License :: OSI Approved :: MIT License
Classifier: Operating System :: OS Independent
Classifier: Programming Language :: Python
Classifier: Programming Language :: Python :: 3.8
Classifier: Programming Language :: Python :: 3.9
Classifier: Programming Language :: Python :: 3.10
Classifier: Topic :: Internet :: WWW/HTTP
Classifier: Topic :: Internet :: WWW/HTTP :: Dynamic Content
Requires-Python: >=3.8
Requires-Dist: allianceauth-app-utils>=1.16.1
Requires-Dist: allianceauth>=3
Requires-Dist: django-eveuniverse>=0.19
